bitclout/Clout.py
bitclout/Diamonds.py
bitclout/Posts.py
bitclout/Route.py
bitclout/Users.py
bitclout/__init__.py
bitclout-0.0.8.dist-info/LICENSE
bitclout-0.0.8.dist-info/METADATA
bitclout-0.0.8.dist-info/WHEEL
bitclout-0.0.8.dist-info/top_level.txt
bitclout-0.0.8.dist-info/RECORD
