Metadata-Version: 2.1
Name: bitclout
Version: 0.0.8
Summary: A python module for bitclout
Home-page: UNKNOWN
Author: ItsAditya (https://bitclout.com/u/ItsAditya)
Author-email: <chaudharyaditya0005@gmail.com>
License: UNKNOWN
Keywords: python,bitclout,social media,crypto,blockchain,decentralisation
Platform: UNKNOWN
Classifier: Development Status :: 1 - Planning
Classifier: Intended Audience :: Developers
Classifier: Programming Language :: Python :: 3
Classifier: Operating System :: Unix
Classifier: Operating System :: MacOS :: MacOS X
Classifier: Operating System :: Microsoft :: Windows
